polar_rcx5_datalink/__init__.py
polar_rcx5_datalink/__main__.py
polar_rcx5_datalink/__version__.py
polar_rcx5_datalink/cli.py
polar_rcx5_datalink/converter.py
polar_rcx5_datalink/datalink.py
polar_rcx5_datalink/exceptions.py
polar_rcx5_datalink/parser.py
polar_rcx5_datalink/utils.py
polar_rcx5_datalink/strava_sync/__init__.py
polar_rcx5_datalink/strava_sync/app.py
polar_rcx5_datalink/strava_sync/uploader.py
polar_rcx5_datalink/strava_sync/static/images/btn_strava_connectwith.png
polar_rcx5_datalink/strava_sync/templates/authorization.html
polar_rcx5_datalink/strava_sync/templates/base.html
polar_rcx5_datalink/strava_sync/templates/index.html
polar_rcx5_datalink-0.1.5.dist-info/LICENSE
polar_rcx5_datalink-0.1.5.dist-info/METADATA
polar_rcx5_datalink-0.1.5.dist-info/WHEEL
polar_rcx5_datalink-0.1.5.dist-info/entry_points.txt
polar_rcx5_datalink-0.1.5.dist-info/top_level.txt
polar_rcx5_datalink-0.1.5.dist-info/RECORD
