Metadata-Version: 2.1
Name: polar-rcx5-datalink
Version: 0.1.5
Summary: Polar RCX5 training session exporter
Home-page: https://github.com/purpledot/polar-rcx5-datalink
Author: purpledot
Author-email: getinax@gmail.com
License: Unlicense
Platform: UNKNOWN
Classifier: License :: Public Domain
Classifier: Programming Language :: Python
Classifier: Programming Language :: Python :: 3
Classifier: Programming Language :: Python :: 3.7
Requires-Python: >=3.7.0
Requires-Dist: click (>=7)
Requires-Dist: flask (>=1.0.2)
Requires-Dist: geopy (>=1.17.0)
Requires-Dist: loguru (>=0.2.5)
Requires-Dist: pytz (>=2018.7)
Requires-Dist: pyusb (>=1.0.2)
Requires-Dist: requests (>=2.20.1)
Requires-Dist: timezonefinder (>=3.3.0)
Requires-Dist: tzlocal (>=1.5.1)
Provides-Extra: dev
Requires-Dist: pytest ; extra == 'dev'
